CHANGELOG.md
LICENSE
MANIFEST.in
README.md
moi_config.txt
setup.py
example/moi.js
example/moi_example.html
example/moi_group.html
example/moi_list.js
example/moi_result.html
example/webserver.py
moi/__init__.py
moi/context.py
moi/group.py
moi/job.py
moi/websocket.py
moi.egg-info/PKG-INFO
moi.egg-info/SOURCES.txt
moi.egg-info/dependency_links.txt
moi.egg-info/requires.txt
moi.egg-info/top_level.txt
moi/support_files/moi.js
moi/support_files/moi_list.js
moi/test/test_group.py
moi/test/test_job.py
scripts/moi