Metadata-Version: 1.1
Name: moi
Version: 0.2.0
Summary: Compute ninja
Home-page: http://github.com/biocore/mustached-octo-ironman
Author: Qiita development team
Author-email: mcdonadt@colorado.edu
License: BSD
Platform: UNKNOWN
Classifier: Development Status :: 4 - Beta
Classifier: License :: OSI Approved :: BSD License
Classifier: Topic :: Software Development :: Libraries :: Python Modules
Classifier: Programming Language :: Python
Classifier: Programming Language :: Python :: 2.7
Classifier: Programming Language :: Python :: Implementation :: CPython
Classifier: Operating System :: OS Independent
Classifier: Operating System :: POSIX :: Linux
Classifier: Operating System :: MacOS :: MacOS X
